examcode/__init__.py
examcode/program1.py
examcode/program2.py
examcode/program3.py
examcode/program4.py
examcode/program5.py
examcode/program6.py
examcode/program7.py
examcode/program8.py
examcode/program9.py
examcode-0.1.0.dist-info/METADATA
examcode-0.1.0.dist-info/WHEEL
examcode-0.1.0.dist-info/top_level.txt
examcode-0.1.0.dist-info/RECORD
