Metadata-Version: 2.4
Name: examcode
Version: 0.1.0
Summary: Contains 9 exam programs accessible via code()
Author: Your Name
Classifier: Programming Language :: Python :: 3
Classifier: Operating System :: OS Independent
Dynamic: author
Dynamic: classifier
Dynamic: description
Dynamic: description-content-type
Dynamic: summary
